{
    "version": "0.44.2",
    "architecture": {
        "64bit": {
            "url": "https://github.com/obstalabs/hiveram-dist/releases/download/v0.44.2/workledger_0.44.2_windows_amd64.zip",
            "bin": [
                "workledger.exe"
            ],
            "hash": "7a83a7267a71942ca6c85d40e6bb06d21236287d96f4559d0ea649d1f3db1d64"
        },
        "arm64": {
            "url": "https://github.com/obstalabs/hiveram-dist/releases/download/v0.44.2/workledger_0.44.2_windows_arm64.zip",
            "bin": [
                "workledger.exe"
            ],
            "hash": "9d606c8d070af84057c735d87e563a1017becfcac2f1966c67ef1b60c9f64afd"
        }
    },
    "homepage": "https://hiveram.com",
    "license": "Proprietary",
    "description": "Hiveram ledger plane for work orders, claims, release bundles, and WEO attribution"
}
