{
    "version": "0.13.0",
    "architecture": {
        "64bit": {
            "url": "https://github.com/obstalabs/hiveram-dist/releases/download/v0.13.0/workledger_0.13.0_windows_amd64.zip",
            "bin": [
                "workledger.exe"
            ],
            "hash": "947eb0b060d920d7a730ce413f4bf675d8caa3decac8072bb13834b9aff477c7"
        },
        "arm64": {
            "url": "https://github.com/obstalabs/hiveram-dist/releases/download/v0.13.0/workledger_0.13.0_windows_arm64.zip",
            "bin": [
                "workledger.exe"
            ],
            "hash": "2137a32e9860d9079d9124d6cec83d7f5d17fc4a2eb96425fea0ca9a3f336ddd"
        }
    },
    "homepage": "https://hiveram.com",
    "license": "Proprietary",
    "description": "Hiveram ledger plane for work orders, claims, release bundles, and WEO attribution"
}
